circular_api/__init__.py
circular_api/circular_api.py
circular_api/circular_exception.py
circular_api/helper.py
circular_api/nag_functions.py
circular_api-1.0.88.dist-info/LICENSE
circular_api-1.0.88.dist-info/METADATA
circular_api-1.0.88.dist-info/WHEEL
circular_api-1.0.88.dist-info/top_level.txt
circular_api-1.0.88.dist-info/RECORD
