Metadata-Version: 2.1
Name: circular_api
Version: 1.0.88
Summary: Circular Blockchain API written in Python 3
Home-page: https://github.com/dannydenovi/circular-python-sdk
Author: Danny De Novi
Author-email: Danny De Novi <dannydenovi29@gmail.com>
Project-URL: Homepage, https://github.com/dannydenovi/circular-python-api
Project-URL: Issues, https://github.com/dannydenovi/circular-python-api/issues
Classifier: Programming Language :: Python :: 3
Classifier: License :: OSI Approved :: MIT License
Classifier: Operating System :: OS Independent
Requires-Python: >=3.9
License-File: LICENSE
Requires-Dist: requests >=2.32.3
Requires-Dist: ecdsa >=0.19.0
